ldaputil/__init__.py
ldaputil/main.py
ldaputil-40.0.0.dist-info/licenses/LICENSE
ldaputil-40.0.0.dist-info/METADATA
ldaputil-40.0.0.dist-info/WHEEL
ldaputil-40.0.0.dist-info/top_level.txt
ldaputil-40.0.0.dist-info/RECORD
